ypricemagic__mypyc.cpython-313-x86_64-linux-musl.so
y/ENVIRONMENT_VARIABLES.cpython-313-x86_64-linux-musl.so
y/ENVIRONMENT_VARIABLES.py
y/__init__.py
y/_decorators.py
y/cli.py
y/constants.py
y/contracts.py
y/convert.cpython-313-x86_64-linux-musl.so
y/convert.py
y/datatypes.py
y/exceptions.cpython-313-x86_64-linux-musl.so
y/exceptions.py
y/monkey_patches.py
y/networks.cpython-313-x86_64-linux-musl.so
y/networks.py
y/py.typed
y/time.py
y/_db/__init__.py
y/_db/brownie.cpython-313-x86_64-linux-musl.so
y/_db/brownie.py
y/_db/common.py
y/_db/config.cpython-313-x86_64-linux-musl.so
y/_db/config.py
y/_db/decorators.cpython-313-x86_64-linux-musl.so
y/_db/decorators.py
y/_db/entities.py
y/_db/exceptions.py
y/_db/log.py
y/_db/structs.py
y/_db/utils/__init__.py
y/_db/utils/_ep.py
y/_db/utils/asyncpg.py
y/_db/utils/bulk.py
y/_db/utils/contract.py
y/_db/utils/logs.py
y/_db/utils/price.py
y/_db/utils/stringify.cpython-313-x86_64-linux-musl.so
y/_db/utils/stringify.py
y/_db/utils/token.py
y/_db/utils/traces.py
y/_db/utils/utils.py
y/classes/__init__.py
y/classes/_abc.py
y/classes/common.py
y/classes/singleton.py
y/interfaces/ERC20.py
y/interfaces/__init__.py
y/interfaces/multicall2.py
y/interfaces/balancer/WeightedPool.py
y/interfaces/balancer/__init__.py
y/interfaces/compound/__init__.py
y/interfaces/compound/unitroller.py
y/interfaces/curve/CurveRegistry.py
y/interfaces/curve/__init__.py
y/interfaces/uniswap/__init__.py
y/interfaces/uniswap/factoryv2.py
y/interfaces/uniswap/quoterv3.py
y/interfaces/uniswap/velov2.py
y/prices/__init__.py
y/prices/band.py
y/prices/chainlink.py
y/prices/convex.py
y/prices/gearbox.py
y/prices/magic.py
y/prices/one_to_one.py
y/prices/pendle.py
y/prices/popsicle.py
y/prices/rkp3r.py
y/prices/solidex.py
y/prices/synthetix.py
y/prices/yearn.py
y/prices/dex/__init__.py
y/prices/dex/genericamm.py
y/prices/dex/mooniswap.py
y/prices/dex/solidly.py
y/prices/dex/velodrome.py
ypricemagic-5.2.1.dist-info/METADATA
ypricemagic-5.2.1.dist-info/WHEEL
ypricemagic-5.2.1.dist-info/entry_points.txt
ypricemagic-5.2.1.dist-info/top_level.txt
ypricemagic-5.2.1.dist-info/RECORD
ypricemagic-5.2.1.dist-info/licenses/LICENSE.txt
