Metadata-Version: 2.4
Name: ypricemagic
Version: 5.2.1
Summary: Use this tool to extract historical on-chain price data from an archive node. Shoutout to @bantg and @nymmrx for their awesome work on yearn-exporter that made this library possible.
Home-page: https://github.com/BobTheBuidler/ypricemagic
Author: BobTheBuidler
Author-email: bobthebuidlerdefi@gmail.com
License: MIT
Classifier: Intended Audience :: Developers
Classifier: Programming Language :: Python :: 3
Classifier: Programming Language :: Python :: 3.9
Classifier: Programming Language :: Python :: 3.10
Classifier: Programming Language :: Python :: 3.11
Classifier: Programming Language :: Python :: 3.12
Classifier: Programming Language :: Python :: 3.13
Classifier: Programming Language :: Python :: Implementation :: CPython
Classifier: Operating System :: OS Independent
Classifier: Topic :: Software Development :: Libraries
Requires-Python: >=3.10,<3.14
License-File: LICENSE.txt
Requires-Dist: aiosqlite==0.22.1
Requires-Dist: asyncpg<0.32,>=0.31
Requires-Dist: bobs_lazy_logging==0.0.5
Requires-Dist: cchecksum<1,>=0.0.3
Requires-Dist: checksum_dict<3,>=2.1.9
Requires-Dist: dank_mids==4.20.195
Requires-Dist: eth-brownie==1.22.0.dev2
Requires-Dist: eth_retry>=0.2.1
Requires-Dist: evmspec>=0.3.4
Requires-Dist: ez-a-sync<1,>=0.33.10
Requires-Dist: faster-eth-abi<6,>=5.2.12
Requires-Dist: faster-eth-utils
Requires-Dist: inflection<0.6,>=0.1
Requires-Dist: joblib>=1.0.1
Requires-Dist: multicall>=0.8.2
Requires-Dist: pony
Requires-Dist: pony-stubs==0.5.2
Requires-Dist: python-dateutil
Requires-Dist: typed-envs<0.3,>=0.2.2
Dynamic: author
Dynamic: author-email
Dynamic: classifier
Dynamic: description
Dynamic: description-content-type
Dynamic: home-page
Dynamic: license
Dynamic: license-file
Dynamic: requires-dist
Dynamic: requires-python
Dynamic: summary
